sqapy/__init__.py
sqapy/bipartite.py
sqapy/sqa.py
sqapy-0.1.1.dist-info/LICENSE
sqapy-0.1.1.dist-info/WHEEL
sqapy-0.1.1.dist-info/METADATA
sqapy-0.1.1.dist-info/RECORD
