Metadata-Version: 2.1
Name: sqapy
Version: 0.1.1
Summary: Simulated quantum annealing implemented in Python
License: MIT
Author: Hirofumi Tsuruta
Requires-Python: >=3.7,<4.0
Classifier: License :: OSI Approved :: MIT License
Classifier: Programming Language :: Python :: 3
Classifier: Programming Language :: Python :: 3.7
Classifier: Programming Language :: Python :: 3.8
Requires-Dist: numpy (>=1.18.2,<2.0.0)
